simple_archive-0.3.0.dist-info/METADATA
simple_archive-0.3.0.dist-info/WHEEL
simple_archive-0.3.0.dist-info/entry_points.txt
simple_archive-0.3.0.dist-info/licenses/LICENSE
simple_archive/__init__.py
simple_archive/cli.py
simple_archive/file_system.py
simple_archive/simple_archive.py
simple_archive/use_cases.py
simple_archive-0.3.0.dist-info/RECORD
